ccc007/__init__.py
ccc007/tools.py
ccc007-0.1.8.dist-info/LICENSE
ccc007-0.1.8.dist-info/METADATA
ccc007-0.1.8.dist-info/WHEEL
ccc007-0.1.8.dist-info/top_level.txt
ccc007-0.1.8.dist-info/RECORD
