Metadata-Version: 2.1
Name: ccc007
Version: 0.1.8
Summary: ccc007的工具
Home-page: https://github.com/1492949083/repo
Author: ccc007
Author-email: mengchao704653@gmail.com
License-File: LICENSE
Requires-Dist: pywin32
Requires-Dist: numpy
Requires-Dist: Pillow
